Metadata-Version: 1.0
Name: learnfuntest
Version: 0.1
Summary: The funniest joke in the world to beginner
Home-page: http://github.com/storborg/funniest
Author: Flying Circus
Author-email: flyingcircus@example.com
License: MIT
Platform: UNKNOWN
